{
  "id": 2001,
  "name": "简易头盔",
  "description": "用废金属拼凑的防护头盔",
  "icon_path": "",
  "value": 0,
  "weight": 1.5,
  "fragments": [
    {
      "kind": "economy",
      "rarity": "common"
    },
    {
      "kind": "stacking",
      "stackable": false,
      "max_stack": 1
    },
    {
      "kind": "equip",
      "slots": [
        "head"
      ],
      "level_requirement": 1,
      "equip_effect_ids": [],
      "unequip_effect_ids": []
    },
    {
      "kind": "appearance",
      "definition": {
        "equip_slot": "head",
        "visual_asset": "builtin:item:head",
        "attach_target": "head",
        "presentation_mode": "replace_region",
        "hide_base_regions": [
          "head"
        ],
        "preview_transform": {},
        "tint": "#7b8270"
      }
    },
    {
      "kind": "durability",
      "durability": 30,
      "max_durability": 30,
      "repairable": true,
      "repair_materials": [
        {
          "item_id": 1010,
          "count": 2
        }
      ]
    },
    {
      "kind": "attribute_modifiers",
      "attributes": {
        "defense": 2.0,
        "insulation": 0.1
      }
    }
  ]
}
